{"stats":{"minecraft:mined":{"minecraft:grass_block":1,"minecraft:blue_orchid":1,"minecraft:cornflower":2},"minecraft:custom":{"minecraft:jump":32,"minecraft:time_since_rest":2758,"minecraft:climb_one_cm":12,"minecraft:leave_game":3,"minecraft:play_time":2758,"minecraft:sprint_one_cm":4982,"minecraft:damage_taken":20,"minecraft:time_since_death":2758,"minecraft:walk_one_cm":5447,"minecraft:total_world_time":3089,"minecraft:fall_one_cm":1240,"minecraft:fly_one_cm":7377},"minecraft:picked_up":{"minecraft:blue_orchid":1,"minecraft:cornflower":2,"minecraft:dirt":1},"minecraft:used":{"minecraft:dirt":1,"minecraft:cornflower":2,"minecraft:blue_orchid":1}},"DataVersion":3218}